[
    {
        "id": 1,
        "name": "New Launch Boys Jeans Comfortable Long Pants Fit Stretch Distressed Jogger Kids Jeans",
        "image": "https://i.postimg.cc/W36hqmgm/1.png",
        "price": 10.99,
        "category": "jeans"
    },
    {
        "id": 2,
        "name": "Wholesale High  Quality Custom Fabric Black Boys Stretch Slim Fit Denim Pants Kids Jeans",
        "image": "https://i.postimg.cc/52THh2fz/2.png",
        "price": 10.99,
        "category": "jeans"
    },
    {
        "id": 3,
        "name": "OEM Service Stretch Casual Elastic waistband Blue Washed Slim Fit Boys Joggers Kids Jeans",
        "image": "https://i.postimg.cc/zB1yf2bX/3.png",
        "price": 10.99,
        "category": "jeans"
    },
    {
        "id": 4,
        "name": "Factory Price New Design Comfortable Wide Leg Pants Denim Girls Jeans",
        "image": "https://i.postimg.cc/pdj9RMd6/4.png",
        "price": 10.99,
        "category": "jeans"
    },
    {
        "id": 5,
        "name": "Factory supply golden supply soft stretchy denim pants regular fit kids jeans",
        "image": "https://i.postimg.cc/D0vmrWP9/5.png",
        "price": 10.99,
        "category": "jeans"
    },
    {
        "id": 6,
        "name": "High quality Competitive Price Custom Sky Blue Denim Jeans Flare Denim Pants For Girls",
        "image": "https://i.postimg.cc/T1t1CRkp/6.png",
        "price": 10.99,
        "category": "jeans"
    },
    {
        "id": 7,
        "name": "Wholesale customize ripped denim jeans for baby and kids",
        "image": "https://i.postimg.cc/zD7yJjJ8/7.png",
        "price": 10.99,
        "category": "jeans"
    },
    {
        "id": 8,
        "name": "INS Hot Sale Stretchy Grey Denim Boys Jeans",
        "image": "https://i.postimg.cc/qM7zg3Rn/8.png",
        "price": 10.99,
        "category": "jeans"
    },
    {
        "id": 9,
        "name": "Children's trend heavyweight denim pants for girls with multiple pockets popular design for girls with straight shorts",
        "image": "https://i.postimg.cc/7YQbzZGR/9.png",
        "price": 10.99,
        "category": "jeans"
    },
    {
        "id": 10,
        "name": "Custom Full Length Slim Fit Rip Jeans For Children Stretchy Unisex Toddler Denim Pants Boys Jeans",
        "image": "https://i.postimg.cc/t4ZJNGF4/10.png",
        "price": 10.99,
        "category": "jeans"
    },
    {
        "id": 11,
        "name": "New Casual Green Washed Cotton Kids Denim Jogger Pants Plus Size Breathable Kids Jeans",
        "image": "https://i.postimg.cc/W1B39Y76/11.png",
        "price": 10.99,
        "category": "jeans"
    },
    {
        "id": 12,
        "name": "OEM 2024 New Style Kids Clothes Baby Jeans Casual Children Denim Pants for Unisex Boys&Girls Jeans",
        "image": "https://i.postimg.cc/nLqLNKR8/12.png",
        "price": 10.99,
        "category": "jeans"
    },
    {
        "id": 13,
        "name": "New fashion styles boys denim jeans slim fit soft stretch denim pants for children kids jeans",
        "image": "https://i.postimg.cc/4dZ3GKqY/13.png",
        "price": 10.99,
        "category": "jeans"
    },
    {
        "id": 14,
        "name": "Latest Design Elastic Trousers Baby Boy Jeans Casual Custom Cotton Spandex Loose Toddler Boys Jeans",
        "image": "https://i.postimg.cc/G2QmmLnq/14.png",
        "price": 10.99,
        "category": "jeans"
    },
    {
        "id": 15,
        "name": "Multi Styles Teenager New Style Fashion Kids Denim Jeans Pants Hot Sale Casual Wear Loose Flared Cotton Girls Denim Jeans",
        "image": "https://i.postimg.cc/zvGXLsJ5/15.png",
        "price": 10.99,
        "category": "jeans"
    },
    {
        "id": 16,
        "name": "2024 Hot sell Kids Pants Colorful Gradient Elastic Waist Denim Casual Kids Jeans 4-14Y High Quality Straight Big Leg Girls Jeans",
        "image": "https://i.postimg.cc/Y0D2Qd9F/16.png",
        "price": 10.99,
        "category": "jeans"
    },
    {
        "id": 17,
        "name": "Girls jeans spring and autumn new casual fashion children's pants jeans for girls baby girls jeans pants",
        "image": "https://i.postimg.cc/9XLf3Qpf/17.png",
        "price": 10.99,
        "category": "jeans"
    },
    {
        "id": 18,
        "name": "Baby Girl Jean Pants Cotton High Waist Infant Toddler Children Jeans Denim Trousers Long Baby Boys Girls Loose Pant",
        "image": "https://i.postimg.cc/VL5kzPGW/18.png",
        "price": 10.99,
        "category": "jeans"
    },
    {
        "id": 19,
        "name": "Girls Pants Europe and America Fashion Style Jeans Flared Trousers Children Toddler Baby Kids Denim Bell Bottom Boot Cut Pants",
        "image": "https://i.postimg.cc/CLtL1r9T/19.png",
        "price": 10.99,
        "category": "jeans"
    },
    {
        "id": 20,
        "name": "2024 hot selling girls pants niche style children's black splicing pants retro girl bell bottoms",
        "image": "https://i.postimg.cc/4x94hbTK/20.png",
        "price": 10.99,
        "category": "jeans"
    },
    {
        "id": 21,
        "name": "New arrival baby pantyhose knitting girls tights sweet heart baby tights cotton children tights pantyhose with bowknot",
        "image": "https://i.ibb.co/PcryWTD/1.png",
        "price": 10.99,
        "category": "leggings"
    },
    {
        "id": 22,
        "name": "New Style Sweet Big Eyes Pantyhose With Cotton Girls Tights Stockings Baby Pantyhose",
        "image": "https://i.ibb.co/4g87pTD/2.png",
        "price": 10.99,
        "category": "leggings"
    },
    {
        "id": 23,
        "name": "spring kids pantyhose standard baby tights child little girl pantyhose winter baby leggings",
        "image": "https://i.ibb.co/nLwz9wc/3.png",
        "price": 10.99,
        "category": "leggings"
    },
    {
        "id": 24,
        "name": "New Arrival Fashion Solid Colors Pencil Pants Cute Kids Leggings Casual Trousers Baby Girls Pants Girls Tight Leggings",
        "image": "https://i.ibb.co/CPfwM32/4.png",
        "price": 10.99,
        "category": "leggings"
    },
    {
        "id": 25,
        "name": "New Arrival Fashion Solid Colors Pencil Pants Cute Kids Leggings Casual Trousers Baby Girls Pants Girls Tight Leggings",
        "image": "https://i.ibb.co/2M9mbDm/5.png",
        "price": 10.99,
        "category": "leggings"
    },
    {
        "id": 26,
        "name": "Autumn 2024 Kids Girls Fashion Leggings Toddlers Cotton Pants Solid Color Baby Elastic Ribbed Tights",
        "image": "https://i.ibb.co/DpXS0YP/6.png",
        "price": 10.99,
        "category": "leggings"
    },
    {
        "id": 27,
        "name": "Kids Pants Unicorn Legging Girls Trousers Leggings for Girls Legging Elasticity Breathable Soft Print Baby Boy Girls Pants",
        "image": "https://i.ibb.co/GMQqrFc/7.png",
        "price": 10.99,
        "category": "leggings"
    },
    {
        "id": 28,
        "name": "2023 Custom Kids Boys Girls Long Short Sleeve Thick Spandex Sports Fitness Training Running Shorts leggings Tights and Tops Gym",
        "image": "https://i.ibb.co/pWqTs2K/8.png",
        "price": 10.99,
        "category": "leggings"
    },
    {
        "id": 29,
        "name": "Hingto ODM customize yoga pants kids fitness clothing sports clothes child yoga gym leggings for kids",
        "image": "https://i.ibb.co/gvNXzbt/9.png",
        "price": 10.99,
        "category": "leggings"
    },
    {
        "id": 30,
        "name": "Piano Keys Music Black Cat Print Sport Leggings Children Short Yoga Pants Fitness Kids Legging Training Seamless Tights Pants",
        "image": "https://i.ibb.co/fDySRss/10.png",
        "price": 10.99,
        "category": "leggings"
    },
    {
        "id": 31,
        "name": "Little Girl active wear athletic sports wear yoga printed pants yoga tights for children kids clothing girls yoga gym leggings",
        "image": "https://i.ibb.co/k008Cff/11.png",
        "price": 10.99,
        "category": "leggings"
    },
    {
        "id": 32,
        "name": "New Style Custom Bronzing Kids Dance Leggings High Waisted Girls Leggings For 3-12 Years",
        "image": "https://i.ibb.co/6H4yrbt/12.png",
        "price": 10.99,
        "category": "leggings"
    },
    {
        "id": 33,
        "name": "Children Girls Stacked Cotton Leggings Candy Color Kids Girl Stacked Sweatpants Soft Stretchy Yoga Pants",
        "image": "https://i.ibb.co/cTJq5jG/13.png",
        "price": 10.99,
        "category": "leggings"
    },
    {
        "id": 34,
        "name": "Fitness Wear Sport Wear Soft Cotton Rib Knit winter leggings for kids girls Marble Tie Dye pants Kids Yoga Wear",
        "image": "https://i.ibb.co/rwkF67W/14.png",
        "price": 10.99,
        "category": "leggings"
    },
    {
        "id": 35,
        "name": "Wholesale children activewear fitness wear yoga leggings kids activewear kids fitness clothes manufacturer",
        "image": "https://i.ibb.co/TvJTPGP/15.png",
        "price": 10.99,
        "category": "leggings"
    },
    {
        "id": 36,
        "name": "OEM activewear athletic sports wear yoga pants for girls yoga clothes for children custom kids clothing leggings solid color",
        "image": "https://i.ibb.co/P1BDj53/16.png",
        "price": 10.99,
        "category": "leggings"
    },
    {
        "id": 37,
        "name": "2022 Latest Wholesale Kids winter fall Faux Leather Leggings - Black Toddler Girls Stacked Pants Set Can Add Logo With Small Moq",
        "image": "https://i.ibb.co/hYF3D3F/17.png",
        "price": 10.99,
        "category": "leggings"
    },
    {
        "id": 38,
        "name": "2023 Factory milk silk fabric wholesale kid girls high school tights leggings",
        "image": "https://i.ibb.co/YLDRbqJ/18.png",
        "price": 10.99,
        "category": "leggings"
    },
    {
        "id": 39,
        "name": "Custom Kids Adjustable V Neck Pink Sports Bra Fitness Yoga Wear For Kids Girls Activewear Stretchy Yoga Pants Leggings Set",
        "image": "https://i.ibb.co/3phDzQG/19.png",
        "price": 10.99,
        "category": "leggings"
    },
    {
        "id": 40,
        "name": "Hawaii Hibiscus Monstera Leaf Yoga Pants Kids Sport Fitness Short Leggings Girls Seamless Legging Boy Tummy Control Run Tights",
        "image": "https://i.ibb.co/Yk8Zyjr/20.png",
        "price": 10.99,
        "category": "leggings"
    },
    {
        "id": 41,
        "name": "Boy Kids Trendy Clothing Formal Long Sleeve kids Shirts for Cotton",
        "image": "https://i.postimg.cc/B6THJmHT/1.png",
        "price": 10.99,
        "category": "shirt"
    },
    {
        "id": 42,
        "name": "Modern Cozy Kids School Polo Shirts Custom Embroidery Design Cotton Boys T-Shirts Stripe Polo Shirts For 2-14 Years",
        "image": "https://i.postimg.cc/jjJyFxjk/2.png",
        "price": 10.99,
        "category": "shirt"
    },
    {
        "id": 43,
        "name": "Boys Short Sleeves Button Up Preppy Style Polo Shirt For Kidss",
        "image": "https://i.postimg.cc/6pPdc2Bv/3.png",
        "price": 10.99,
        "category": "shirt"
    },
    {
        "id": 44,
        "name": "Professional Manufacture Boys Cartoon Long Sleeve Cotton T Shirt Blouse Tops",
        "image": "https://i.postimg.cc/JnVjwfD7/4.png",
        "price": 10.99,
        "category": "shirt"
    },
    {
        "id": 45,
        "name": "High Quality Women's Oversized Plaid Shirt Fashionable High Quality Women's Blouses & Shirts",
        "image": "https://i.postimg.cc/hvKxvV1H/5.png",
        "price": 10.99,
        "category": "shirt"
    },
    {
        "id": 46,
        "name": "Custom Design Wholesale Children Boutique Clothing Milk Silk Kids Shirts with buttons",
        "image": "https://i.postimg.cc/sxKWh1n1/6.png",
        "price": 10.99,
        "category": "shirt"
    },
    {
        "id": 47,
        "name": "Custom Design Wholesale Children Boutique Clothing Milk Silk Kids Shirts with buttons",
        "image": "https://i.postimg.cc/66hnS19w/7.png",
        "price": 10.99,
        "category": "shirt"
    },
    {
        "id": 48,
        "name": "Customized cotton children polo shirt summer children's clothing fashion printing boy t-shirt",
        "image": "https://i.postimg.cc/CLLkVH18/8.png",
        "price": 10.99,
        "category": "shirt"
    },
    {
        "id": 49,
        "name": "New arrival 2392-6 yellow children's clothing luxury,good price kids clothing wholesale,High quality baby girl clothing sets",
        "image": "https://i.postimg.cc/VLGMsrrV/9.png",
        "price": 10.99,
        "category": "shirt"
    },
    {
        "id": 50,
        "name": "New arrival 2392-1 autumn long sleeve t shirts for girls,fashion children's clothing luxury,printing kids clothing wholesale",
        "image": "https://i.postimg.cc/6p8Z8WC5/10.png",
        "price": 10.99,
        "category": "shirt"
    },
    {
        "id": 51,
        "name": "Stilnyashka 2381-1 fashion girls clothing sets,summer toddler girls clothing sets,girls t-shirts and toddler girls shorts set",
        "image": "https://i.postimg.cc/JzSkJfQ3/11.png",
        "price": 10.99,
        "category": "shirt"
    },
    {
        "id": 52,
        "name": "100% cotton children clothes baby boy shirts Summer cotton style boys' short sleeve shirt soft comfortable striped lapel",
        "image": "https://i.postimg.cc/pd8nBs0w/12.png",
        "price": 10.99,
        "category": "shirt"
    },
    {
        "id": 53,
        "name": "Wholesale Boys' Spring and Autumn Shirts Engineering Vehicle Printing Boys Shirt Soft Cotton Lapel Children Casual Shirts",
        "image": "https://i.postimg.cc/d1YZNGpL/13.png",
        "price": 10.99,
        "category": "shirt"
    },
    {
        "id": 54,
        "name": "High Quality Trendy Boys Pumpkin Plaid Blouse Kids Collar Button Long Sleeve Shirts Baby Warm Top with Pocket",
        "image": "https://i.postimg.cc/j54wpLYv/14.png",
        "price": 10.99,
        "category": "shirt"
    },
    {
        "id": 55,
        "name": "Custom Logo Long Sleeve Children Kids Clothes Tops Plaid Shirt Boy Solid Color Casual Spring and Autumn Blouse Shirts",
        "image": "https://i.postimg.cc/PJfpTTtH/15.png",
        "price": 10.99,
        "category": "shirt"
    },
    {
        "id": 56,
        "name": "Boys Casual Denim Shirts Long Sleeved Lapel Casual Children Shirt Spring Autumn Handsome Boys Shirt Tops",
        "image": "https://i.postimg.cc/QC6BMwtT/16.png",
        "price": 10.99,
        "category": "shirt"
    },
    {
        "id": 57,
        "name": "2024 new boys and girls spring autumn baby cotton striped shirts long-sleeved coat kids plaid dress shirt",
        "image": "https://i.postimg.cc/bYLSLDTw/17.png",
        "price": 10.99,
        "category": "shirt"
    },
    {
        "id": 58,
        "name": "Wholesaler Spring Summer baby t-shirts babycbaby boy polo t-shirts",
        "image": "https://i.postimg.cc/Prxp7X3z/18.png",
        "price": 10.99,
        "category": "shirt"
    },
    {
        "id": 59,
        "name": "Boys' short-sleeved shirt summer new children's clothes casual and comfortable beach island children's flower shirt outer wear",
        "image": "https://i.postimg.cc/28KbRsgp/19.png",
        "price": 10.99,
        "category": "shirt"
    },
    {
        "id": 60,
        "name": "New Arrival Spring Kids CLothes Autumn Long Sleeve Cotton Print Cartoon Baby Boy Shirt",
        "image": "https://i.postimg.cc/wjRt6Wd1/20.png",
        "price": 10.99,
        "category": "shirt"
    },
    {
        "id": 61,
        "name": "Good Sale Solid Custom Picture Printing Color Cotton Kids Boys Long Sleeve T Shirts for Boys",
        "image": "https://i.postimg.cc/vByTQbQB/1.png",
        "price": 10.99,
        "category": "tshirt"
    },
    {
        "id": 62,
        "name": "children's clothing toddler boys t-shirt baby tshirts cotton kids summer tshirts boys clothes wholesale",
        "image": "https://i.postimg.cc/50m0yT0m/2.png",
        "price": 10.99,
        "category": "tshirt"
    },
    {
        "id": 63,
        "name": "2024 High Quality 100% cotton printed cute animal and letter 3 years short sleeve t-shirts for boy",
        "image": "https://i.postimg.cc/mrChftWJ/3.png",
        "price": 10.99,
        "category": "tshirt"
    },
    {
        "id": 64,
        "name": "Summer Boy Clothes Luminous Dinosaur T-shirt Cotton Cool 2-14 years Boys T-shirts Cartoon",
        "image": "https://i.postimg.cc/cC4JnhtG/4.png",
        "price": 10.99,
        "category": "tshirt"
    },
    {
        "id": 65,
        "name": "Summer Boy Clothes Luminous Dinosaur T-shirt Cotton Cool 2-14 years Boys T-shirts Cartoon",
        "image": "https://i.postimg.cc/NfFMGNw1/5.png",
        "price": 10.99,
        "category": "tshirt"
    },
    {
        "id": 66,
        "name": "Children's Summer Wear Short Sleeved T-shirt Dinosaur Patch Embroidered Boys Striped T Shirt for Kids",
        "image": "https://i.postimg.cc/024Nzp8h/6.png",
        "price": 10.99,
        "category": "tshirt"
    },
    {
        "id": 67,
        "name": "New Arrival Hot Selling Wholesale Custom Kids Black Oversized Baby Boy Tshirt Summer",
        "image": "https://i.postimg.cc/L8Z8Ln55/7.png",
        "price": 10.99,
        "category": "tshirt"
    },
    {
        "id": 68,
        "name": "Wholesale Short Sleeve Summer Solid Color Shirt With Patch Pocket Unisex Kids Crew Neck T-shirt",
        "image": "https://i.postimg.cc/MTz6C5Df/8.png",
        "price": 10.99,
        "category": "tshirt"
    },
    {
        "id": 69,
        "name": "Printed Boys White T shirt Baby Boy Summer Clothes Cotton Wear Short Sleeve Kids T shirt Kids Cartoon Clothing",
        "image": "https://i.postimg.cc/V64fmtGG/9.png",
        "price": 10.99,
        "category": "tshirt"
    },
    {
        "id": 70,
        "name": "Kids tshirt Cotton Boys Clothes Baby Boy T-shirts with Cartoon Printing Cute Baby Top Summer Toddler Boys Clothing Kids T shirt",
        "image": "https://i.postimg.cc/cCHsHJPs/10.png",
        "price": 10.99,
        "category": "tshirt"
    },
    {
        "id": 71,
        "name": "New arrival 100% cotton kids t shirts personalized kids t shirts boys full round neck t shirts",
        "image": "https://i.postimg.cc/Gt5bsC1v/11.png",
        "price": 10.99,
        "category": "tshirt"
    },
    {
        "id": 72,
        "name": "High Quality Cotton Striped Boys T shirts Dragon Printing Children's T shirt Kids Summer Clothes Cute Baby Boy Workout",
        "image": "https://i.postimg.cc/rynVHStz/12.png",
        "price": 10.99,
        "category": "tshirt"
    },
    {
        "id": 73,
        "name": "Custom Design Toddler T-shirts And Polo Shirts 100% Cotton Soft Baby Boys Clothing Boys T-shirts",
        "image": "https://i.postimg.cc/ncXFfCv2/13.png",
        "price": 10.99,
        "category": "tshirt"
    },
    {
        "id": 74,
        "name": "Summer Girls T-shirt Baby T-shirt Thin Letter Print Boys Short Sleeve T-Shirt",
        "image": "https://i.postimg.cc/c4Psx0hS/14.png",
        "price": 10.99,
        "category": "tshirt"
    },
    {
        "id": 75,
        "name": "kids tee shirts boys tahirt white tshirt branded cotton children's t-shirts",
        "image": "https://i.postimg.cc/rpkM4j7Z/15.png",
        "price": 10.99,
        "category": "tshirt"
    },
    {
        "id": 76,
        "name": "Best New Product of 2024 100% cotton letter printing cute boys' short-sleeved t-shirts for Mother's Day",
        "image": "https://i.postimg.cc/8CmDmWSp/16.png",
        "price": 10.99,
        "category": "tshirt"
    },
    {
        "id": 77,
        "name": "Wholesale Children's Clothing Summer Short Sleeve Top Casual Pullover Boys Cotton T-shirt for Kids",
        "image": "https://i.postimg.cc/fLWs2Lzx/17.png",
        "price": 10.99,
        "category": "tshirt"
    },
    {
        "id": 78,
        "name": "New Fashion summer short cool printed pattern boys t-shirts for 2-14 years old",
        "image": "https://i.postimg.cc/xCs2W28B/18.png",
        "price": 10.99,
        "category": "tshirt"
    },
    {
        "id": 79,
        "name": "Best New Product of 2024 casual short sleeve custom letter printing t-shirt boys for Father's Day",
        "image": "https://i.postimg.cc/cCrSWb8C/19.png",
        "price": 10.99,
        "category": "tshirt"
    },
    {
        "id": 80,
        "name": "Summer Kids Clothing Boys 100% Cotton Knitted Black Short Sleeve T-Shirts",
        "image": "https://i.postimg.cc/mkJGgyQw/20.png",
        "price": 10.99,
        "category": "tshirt"
    },
    {
        "id": 81,
        "name": "180 Grams 100% Cotton Plain Soft Custom School T Shirt Polo Neck Knitted Kids Polo T-Shirt Printed For Children",
        "image": "https://i.postimg.cc/NGHDCwMn/1.png",
        "price": 10.99,
        "category": "polo"
    },
    {
        "id": 82,
        "name": "180 Grams 100% Cotton Plain Soft Custom School T Shirt Polo Neck Knitted Kids Polo T-Shirt Printed For Children",
        "image": "https://i.postimg.cc/pXMZg15L/2.png",
        "price": 10.99,
        "category": "polo"
    },
    {
        "id": 83,
        "name": "Customized Pure color short sleeved T shirts Children POLO lapel shirt for 2-14T kids shirt",
        "image": "https://i.postimg.cc/HnXtrbRm/3.png",
        "price": 10.99,
        "category": "polo"
    },
    {
        "id": 84,
        "name": "Customized Pure color short sleeved T shirts Children POLO lapel shirt for 2-14T kids shirt",
        "image": "https://i.postimg.cc/1tLHRvWM/4.png",
        "price": 10.99,
        "category": "polo"
    },
    {
        "id": 85,
        "name": "Wholesale kids Summer Short Suit Turn Down Collar Clothing Solid polo Top and Bottom Set tshirt set for children Outfits",
        "image": "https://i.postimg.cc/bvrHQ7W3/5.png",
        "price": 10.99,
        "category": "polo"
    },
    {
        "id": 86,
        "name": "Summer Plain Short Sleeves Kids Polo Shirt Boys Solid Tops Cotton Children T-Shirts",
        "image": "https://i.postimg.cc/zG0FHzty/6.png",
        "price": 10.99,
        "category": "polo"
    },
    {
        "id": 87,
        "name": "Summer Plain Short Sleeves Kids Polo Shirt Boys Solid Tops Cotton Children T-Shirts",
        "image": "https://i.postimg.cc/DyQgFd1d/7.png",
        "price": 10.99,
        "category": "polo"
    },
    {
        "id": 88,
        "name": "New Children's Ollie Velvet Thick Warm Long-Sleeved Lapel POLO Shirt Boys Hoodies & Sweatshirts",
        "image": "https://i.postimg.cc/mgjG55jv/kids-polo.png",
        "price": 10.99,
        "category": "polo"
    },
    {
        "id": 89,
        "name": "Hot sale Tops Casual Design Boy T Shirts for Kids for Boys 100% Cotton T-Shirt Polo Neck Kid Boys Girls Polo Shirt",
        "image": "https://i.postimg.cc/QMzgS6rs/9.png",
        "price": 10.99,
        "category": "polo"
    },
    {
        "id": 90,
        "name": "Hot sale Tops Casual Design Boy T Shirts for Kids for Boys 100% Cotton T-Shirt Polo Neck Kid Boys Girls Polo Shirt",
        "image": "https://i.postimg.cc/RFn7YcMt/10.png",
        "price": 10.99,
        "category": "polo"
    },
    {
        "id": 91,
        "name": "Hot sale Tops Casual Design Boy T Shirts for Kids for Boys 100% Cotton T-Shirt Polo Neck Kid Boys Girls Polo Shirt",
        "image": "https://i.postimg.cc/8cQRgj50/11.png",
        "price": 10.99,
        "category": "polo"
    },
    {
        "id": 92,
        "name": "OEM Factory Wholesale Original Boys Customized T-shirts kids Wear Summer New Boys Fashion Embroidered POLO Shirt",
        "image": "https://i.postimg.cc/MH7y6qfK/12.png",
        "price": 10.99,
        "category": "polo"
    },
    {
        "id": 93,
        "name": "OEM Factory Wholesale Original Boys Customized T-shirts kids Wear Summer New Boys Fashion Embroidered POLO Shirt",
        "image": "https://i.postimg.cc/wxL5cc48/13.png",
        "price": 10.99,
        "category": "polo"
    },
    {
        "id": 94,
        "name": "OEM Factory Wholesale Original Boys Customized T-shirts kids Wear Summer New Boys Fashion Embroidered POLO Shirt",
        "image": "https://i.postimg.cc/4NG687jK/14.png",
        "price": 10.99,
        "category": "polo"
    },
    {
        "id": 95,
        "name": "OEM Factory Wholesale Original Boys Customized T-shirts kids Wear Summer New Boys Fashion Embroidered POLO Shirt",
        "image": "https://i.postimg.cc/SNGWHQpg/15.png",
        "price": 10.99,
        "category": "polo"
    },
    {
        "id": 96,
        "name": "Hot Sale Boy Polo Shirt for Kids for Boys Girls 100% Cotton T-Shirt Polo Neck Kid Boys Polo Shirt",
        "image": "https://i.postimg.cc/CxLj0yhS/16.png",
        "price": 10.99,
        "category": "polo"
    },
    {
        "id": 97,
        "name": "Children's short-sleeved shorts, home service suits, children's lapel air-conditioning clothing wholesale",
        "image": "https://i.postimg.cc/L8Cj6y5f/17.png",
        "price": 10.99,
        "category": "polo"
    },
    {
        "id": 98,
        "name": "Summer 100% cotton shorts primary kindergarten gym suit leisure polo kids school uniforms Customize logo embroidery",
        "image": "https://i.postimg.cc/ZqWp9rvQ/18.png",
        "price": 10.99,
        "category": "polo"
    },
    {
        "id": 99,
        "name": "2024 hot selling high quality custom middle high school sports uniforms tracksuit college students t shirts",
        "image": "https://i.postimg.cc/R02fwNcZ/19.png",
        "price": 10.99,
        "category": "polo"
    },
    {
        "id": 100,
        "name": "Wholesale Children summer wear Boys Kids T-shirts Polo Shirts",
        "image": "https://i.postimg.cc/cHY3h0mM/20.png",
        "price": 10.99,
        "category": "polo"
    },
    {
        "id": 101,
        "name": "Summer Children Clothes Pure Cotton Boys Shorts Solid color Kids Clothes Outfits Summer Shorts",
        "image": "https://i.postimg.cc/XvNsZLR3/1.png",
        "price": 10.99,
        "category": "shorts"
    },
    {
        "id": 102,
        "name": "Summer Children Clothes Pure Cotton Boys Shorts Solid color Kids Clothes Outfits Summer Shorts",
        "image": "https://i.postimg.cc/8CytLWGv/2.png",
        "price": 10.99,
        "category": "shorts"
    },
    {
        "id": 103,
        "name": "High Quality Woven Board Shorts for Kids Quick Dry Casual Beach Shorts with Pockets for Boys China Wholesale Swimwear Beachwear",
        "image": "https://i.postimg.cc/76d9WkfY/3.png",
        "price": 10.99,
        "category": "shorts"
    },
    {
        "id": 104,
        "name": "2024 Customized BoardShorts Logo 100% Polyester Boys' Beach Shorts Quick Dry Casual Pockets Swimwear Beachwear Boy Swim Shorts",
        "image": "https://i.postimg.cc/qRzQwRB5/4.png",
        "price": 10.99,
        "category": "shorts"
    },
    {
        "id": 105,
        "name": "2024 Customized BoardShorts Logo 100% Polyester Boys' Beach Shorts Quick Dry Casual Pockets Swimwear Beachwear Boy Swim Shorts",
        "image": "https://i.postimg.cc/KjTfXHM7/5.png",
        "price": 10.99,
        "category": "shorts"
    },
    {
        "id": 106,
        "name": "2024 Customized BoardShorts Logo 100% Polyester Boys' Beach Shorts Quick Dry Casual Pockets Swimwear Beachwear Boy Swim Shorts",
        "image": "https://i.postimg.cc/MZfdjvFc/6.png",
        "price": 10.99,
        "category": "shorts"
    },
    {
        "id": 107,
        "name": "Custom Cotton Kids Acid Enzyme Wash Denim Casual Jeans Shorts For Girls",
        "image": "https://i.postimg.cc/tC0DdpKB/7.png",
        "price": 10.99,
        "category": "shorts"
    },
    {
        "id": 108,
        "name": "Custom kid clothes girl denim jeans design depaperbag bermuda shorts with blet",
        "image": "https://i.postimg.cc/GhkKq6rd/8.png",
        "price": 10.99,
        "category": "shorts"
    },
    {
        "id": 109,
        "name": "Custom girl kids casual waistband darts denim bermuda shorts with buttons",
        "image": "https://i.postimg.cc/W1TnKSbr/9.png",
        "price": 10.99,
        "category": "shorts"
    },
    {
        "id": 110,
        "name": "Custom girl kids casual waistband darts denim bermuda shorts with buttons",
        "image": "https://i.postimg.cc/9QbpjTrk/10.png",
        "price": 10.99,
        "category": "shorts"
    },
    {
        "id": 111,
        "name": "Custom Quick Dry Baby Boys Swimsuits Beachwear Shorts Toddler Kids Little Boy Surfing Swim Trunks with mesh lining",
        "image": "https://i.postimg.cc/g00KcJh2/11.png",
        "price": 10.99,
        "category": "shorts"
    },
    {
        "id": 112,
        "name": "New selling high quality kids beach shorts quick dry breathable shorts for kids",
        "image": "https://i.postimg.cc/25X71DdF/12.png",
        "price": 10.99,
        "category": "shorts"
    },
    {
        "id": 113,
        "name": "Custom Logo Toddler Boys Beach Swimming Shorts Board Shorts Kids Swim Trunks In Wholesale Price",
        "image": "https://i.postimg.cc/k46F8pfr/13.png",
        "price": 10.99,
        "category": "shorts"
    },
    {
        "id": 114,
        "name": "Custom Logo Toddler Boys Beach Swimming Shorts Board Shorts Kids Swim Trunks In Wholesale Price",
        "image": "https://i.postimg.cc/5y8BKQhn/14.png",
        "price": 10.99,
        "category": "shorts"
    },
    {
        "id": 115,
        "name": "Custom Logo Toddler Boys Beach Swimming Shorts Board Shorts Kids Swim Trunks In Wholesale Price",
        "image": "https://i.postimg.cc/xCwGP34X/15.png",
        "price": 10.99,
        "category": "shorts"
    },
    {
        "id": 116,
        "name": "Summer girls all-match must-have pink shorts, lightweight and breathable, candy-colored cotton trousers for girls",
        "image": "https://i.postimg.cc/h4m1tNXT/16.png",
        "price": 10.99,
        "category": "shorts"
    },
    {
        "id": 117,
        "name": "Cute Custom Camo Design Summer Baby Clothes Cotton Toddler Boys Casual Kid Shorts for Children",
        "image": "https://i.postimg.cc/sDR9QKW8/17.png",
        "price": 10.99,
        "category": "shorts"
    },
    {
        "id": 118,
        "name": "kids's 2024 Spring and Summer 280G Basic Shorts Youth Fashion Brand Loose Pants Summer kids's Short",
        "image": "https://i.postimg.cc/m2N3QMNr/18.png",
        "price": 10.99,
        "category": "shorts"
    },
    {
        "id": 119,
        "name": "kids Plus Size Comfort Sports Wear Shorts Custom Printed Mesh Shorts For kids",
        "image": "https://i.postimg.cc/cLxRTHXB/19.png",
        "price": 10.99,
        "category": "shorts"
    },
    {
        "id": 120,
        "name": "Summer wholesale striped gingham seersucker cotton kids baby boy shorts",
        "image": "https://i.postimg.cc/DwxqNTNk/20.png",
        "price": 10.99,
        "category": "shorts"
    },
    {
        "id": 121,
        "name": "Ropa De Nina Invierno Chaquetas De Invierno Para Ninas Veste Enfant Fille Casacos De Meninas Kids Winter Coats Hooded",
        "image": "https://i.postimg.cc/7YyjNpdn/1.png",
        "price": 10.99,
        "category": "coat"
    },
    {
        "id": 122,
        "name": "Ropa De Nina Invierno Chaquetas De Invierno Para Ninas Veste Enfant Fille Casacos De Meninas Kids Winter Coats Hooded",
        "image": "https://i.postimg.cc/MZBhVWPG/2.png",
        "price": 10.99,
        "category": "coat"
    },
    {
        "id": 123,
        "name": "Ropa De Nina Invierno Chaquetas De Invierno Para Ninas Veste Enfant Fille Casacos De Meninas Kids Winter Coats Hooded",
        "image": "https://i.postimg.cc/sx5qrcQW/3.png",
        "price": 10.99,
        "category": "coat"
    },
    {
        "id": 124,
        "name": "2024 Autumn Stylish Toddler Boys Jackets&Outwear Fashion Hooded Casual Coat Jackets for Boys Kids",
        "image": "https://i.postimg.cc/76Fddc6D/4.png",
        "price": 10.99,
        "category": "coat"
    },
    {
        "id": 125,
        "name": "Wholesale Children's Windproof Windbreak Jacket Autumn Winter Waterproof Coat Boys Kids Outdoor Jackets",
        "image": "https://i.postimg.cc/yYXtpLz4/5.png",
        "price": 10.99,
        "category": "coat"
    },
    {
        "id": 126,
        "name": "2024 New Winter popular Girl Jacket Pettigirl Plain Red Girls Coats Kids Single Breasted Little Girls Winter Coats 1BAG=1PCS",
        "image": "https://i.postimg.cc/XYjhR9VZ/6.png",
        "price": 10.99,
        "category": "coat"
    },
    {
        "id": 127,
        "name": "Stilnyashka 925C8121 hot selling girls coat wholesale,good price baby jackets outwears,Kids Winter Red children's clothing",
        "image": "https://i.postimg.cc/50CkB3mr/7.png",
        "price": 10.99,
        "category": "coat"
    },
    {
        "id": 128,
        "name": "Stilnyashka 5C8000 Double Breasted girls coats and jackets,Little Baby Winter Coats For Girls,fashion children's clothing casual",
        "image": "https://i.postimg.cc/rpbPRb5W/8.png",
        "price": 10.99,
        "category": "coat"
    },
    {
        "id": 139,
        "name": "Fall Winter Children Clothes Baby Boys Plaid Shirts Long Sleeve Kids Coats",
        "image": "https://i.postimg.cc/wMY40mfj/9.png",
        "price": 10.99,
        "category": "coat"
    },
    {
        "id": 130,
        "name": "Nimble In Stock Kids Formal Fall Winter Coats Girls Outdoor Pullover Coat Oatmeal Color Knee Length Outwear Warm Coat",
        "image": "https://i.postimg.cc/hv8ywt6b/10.png",
        "price": 10.99,
        "category": "coat"
    },
    {
        "id": 131,
        "name": "Spring/Autumn Turn-down Collar Coats Parkas Girl coat",
        "image": "https://i.postimg.cc/J7vsFhKW/11.png",
        "price": 10.99,
        "category": "coat"
    },
    {
        "id": 132,
        "name": "Customized Guangzhou spring baby girls fashion solid pockets coat cute children girl trench infant toddler outerwear",
        "image": "https://i.postimg.cc/SNqt9cYZ/12.png",
        "price": 10.99,
        "category": "coat"
    },
    {
        "id": 133,
        "name": "High quality waterproof baby puffer jacket hooded down padded kids winter coat",
        "image": "https://i.postimg.cc/KvNpD4nm/13.png",
        "price": 10.99,
        "category": "coat"
    },
    {
        "id": 134,
        "name": "Boys down coat hooded warm children puffer jacket winter kids down jacket",
        "image": "https://i.postimg.cc/K88qqFNB/14.png",
        "price": 10.99,
        "category": "coat"
    },
    {
        "id": 135,
        "name": "Kids Loose Long Thick Duck Down Jacket Puffer Comfortable Down Jacket Winter Puffy Duck Down Jacket kids winter clothes",
        "image": "https://i.postimg.cc/vZ2PCjqj/15.png",
        "price": 10.99,
        "category": "coat"
    },
    {
        "id": 136,
        "name": "Custom child clothing boy girl winter clothes baby coat outerwear jacket kids",
        "image": "https://i.postimg.cc/25Sh4SCL/16.png",
        "price": 10.99,
        "category": "coat"
    },
    {
        "id": 137,
        "name": "OEM Custom kids coats outwear girl winter warm coats children's toddler girl wear down winter clothes coat jacket kids",
        "image": "https://i.postimg.cc/Zq9fmcXq/17.png",
        "price": 10.99,
        "category": "coat"
    },
    {
        "id": 138,
        "name": "Kids Loose Long Thick Duck Down Jacket Puffer Comfortable Down Jacket Winter Puffy Duck Down Jacket kids winter clothes",
        "image": "https://i.postimg.cc/Jh9pzXW5/18.png",
        "price": 10.99,
        "category": "coat"
    },
    {
        "id": 139,
        "name": "Boy outwear clothing fashion winter children coat boys down coats",
        "image": "https://i.postimg.cc/RhmGczh3/19.png",
        "price": 10.99,
        "category": "coat"
    },
    {
        "id": 140,
        "name": "Fashion winter clothing for kids thick fleece coats children warm down coat",
        "image": "https://i.postimg.cc/D0c66Y4x/20.png",
        "price": 10.99,
        "category": "coat"
    }
    ,
    {
        "id": 141,
        "name": "High quality Boys pants Hip Hop Print Pants Spring and Autumn kids coat Pants Casual kids boys overalls",
        "image": "https://i.postimg.cc/hP0kNQwG/1.png",
        "price": 10.99,
        "category": "cargo"
    },
    {
        "id": 142,
        "name": "High quality Boys pants Hip Hop Print Pants Spring and Autumn kids coat Pants Casual kids boys overalls",
        "image": "https://i.postimg.cc/XY7RW7Sk/2.png",
        "price": 10.99,
        "category": "cargo"
    },
    {
        "id": 143,
        "name": "High quality Boys pants Hip Hop Print Pants Spring and Autumn kids coat Pants Casual kids boys overalls",
        "image": "https://i.postimg.cc/FHW2H5h5/3.png",
        "price": 10.99,
        "category": "cargo"
    },
    {
        "id": 144,
        "name": "Black Tactical Men'S Trending Stretching Polyester Kids Work Bohemian Pallazzo Min 1 Pice Men Plain Dyed Cargo Pants",
        "image": "https://i.postimg.cc/HsHGS96K/4.png",
        "price": 10.99,
        "category": "cargo"
    },
    {
        "id": 145,
        "name": "Customized Spring And Autumn Child Clothing 100% Cotton Camouflage Toddler Clothes Kids Boy Cargo Pants",
        "image": "https://i.postimg.cc/XvrtZHvZ/5.png",
        "price": 10.99,
        "category": "cargo"
    },
    {
        "id": 146,
        "name": "Wholesale Loose Cargo Pants Men Denim Cargo Pants Men'S Stripe Trousers Pants With Multi Pockets Loose Jeans For Men",
        "image": "https://i.postimg.cc/KYCwtPK0/6.png",
        "price": 10.99,
        "category": "cargo"
    },
    {
        "id": 147,
        "name": "wholesale cargo pants for 3 to 15T Girls Teenager Sets Streetwear Top & jogger cargo pants Girls Clothing set",
        "image": "https://i.postimg.cc/mDMqjPCB/7.png",
        "price": 10.99,
        "category": "cargo"
    },
    {
        "id": 148,
        "name": "wholesale cargo pants for 3 to 15T Girls Teenager Sets Streetwear Top & jogger cargo pants Girls Clothing set",
        "image": "https://i.postimg.cc/8cSY0TmW/8.png",
        "price": 10.99,
        "category": "cargo"
    },
    {
        "id": 149,
        "name": "Autumn Winter Fashion for Kids Loose Flare Pants Girls Solid Pattern Denim Trousers with Long Sleeves Hot Sale",
        "image": "https://i.postimg.cc/d3jfMg5f/9.png",
        "price": 10.99,
        "category": "cargo"
    },
    {
        "id": 150,
        "name": "Wholesale Kids Clothes Child Casual Pants Trousers Cotton Loose Cargo Pants for Teenager Boys",
        "image": "https://i.postimg.cc/9XdKqqcB/10.png",
        "price": 10.99,
        "category": "cargo"
    },
    {
        "id": 151,
        "name": "Factory Wholesale Spring Autumn Kids Pants Trousers New Casual Loose Boys Girls Denim Jeans",
        "image": "https://i.postimg.cc/X7nhK7J6/11.png",
        "price": 10.99,
        "category": "cargo"
    },
    {
        "id": 152,
        "name": "Baby Casual New Pants for Boys and Girls 2024 Korean Edition Large Pocket Drawstring Loose Workwear Pants",
        "image": "https://i.postimg.cc/GhzfXw88/12.png",
        "price": 10.99,
        "category": "cargo"
    },
    {
        "id": 153,
        "name": "Baby Casual New Pants for Boys and Girls 2024 Korean Edition Large Pocket Drawstring Loose Workwear Pants",
        "image": "https://i.postimg.cc/vZBNjqfP/13.png",
        "price": 10.99,
        "category": "cargo"
    },
    {
        "id": 154,
        "name": "Summer style Solid color work Pants Kids big pocket casual pants Girls Boys Solid cargo pants",
        "image": "https://i.postimg.cc/YCssw6xt/14.png",
        "price": 10.99,
        "category": "cargo"
    },
    {
        "id": 155,
        "name": "Summer style Solid color work Pants Kids big pocket casual pants Girls Boys Solid cargo pants",
        "image": "https://i.postimg.cc/3w0brkLm/15.png",
        "price": 10.99,
        "category": "cargo"
    },
    {
        "id": 156,
        "name": "Summer style Solid color work Pants Kids big pocket casual pants Girls Boys Solid cargo pants",
        "image": "https://i.postimg.cc/vBR24Gjj/16.png",
        "price": 10.99,
        "category": "cargo"
    },
    {
        "id": 157,
        "name": "Summer style Solid color work Pants Kids big pocket casual pants Girls Boys Solid cargo pants",
        "image": "https://i.postimg.cc/pTDG8gMd/17.png",
        "price": 10.99,
        "category": "cargo"
    },
    {
        "id": 158,
        "name": "Summer style Solid color work Pants Kids big pocket casual pants Girls Boys Solid cargo pants",
        "image": "https://i.postimg.cc/3NYLZn3F/18.png",
        "price": 10.99,
        "category": "cargo"
    },
    {
        "id": 159,
        "name": "Summer style Solid color work Pants Kids big pocket casual pants Girls Boys Solid cargo pants",
        "image": "https://i.postimg.cc/fyC8qmLn/19.png",
        "price": 10.99,
        "category": "cargo"
    },
    {
        "id": 160,
        "name": "Summer style Solid color work Pants Kids big pocket casual pants Girls Boys Solid cargo pants",
        "image": "https://i.postimg.cc/mZyprfSX/20.png",
        "price": 10.99,
        "category": "cargo"
    },
    {
        "id": 161,
        "name": "Wholesale customization of your logo oversized street style blank hoodie and sweatshirt for kids",
        "image": "https://i.postimg.cc/SK4TpCTP/1.png",
        "price": 10.99,
        "category": "hoodie"
    },
    {
        "id": 162,
        "name": "Wholesale customization of your logo oversized street style blank hoodie and sweatshirt for kids",
        "image": "https://i.postimg.cc/nL1dVrNh/2.png",
        "price": 10.99,
        "category": "hoodie"
    },
    {
        "id": 163,
        "name": "Wholesale customization of your logo oversized street style blank hoodie and sweatshirt for kids",
        "image": "https://i.postimg.cc/hPHZpH9c/3.png",
        "price": 10.99,
        "category": "hoodie"
    },
    {
        "id": 164,
        "name": "Wholesale customization of your logo oversized street style blank hoodie and sweatshirt for kids",
        "image": "https://i.postimg.cc/pLzG7qZ8/4.png",
        "price": 10.99,
        "category": "hoodie"
    },
    {
        "id": 165,
        "name": "Wholesale customization of your logo oversized street style blank hoodie and sweatshirt for kids",
        "image": "https://i.postimg.cc/bJNmZ8jH/5.png",
        "price": 10.99,
        "category": "hoodie"
    },
    {
        "id": 166,
        "name": "Wholesale customization of your logo oversized street style blank hoodie and sweatshirt for kids",
        "image": "https://i.postimg.cc/Px32ZcXG/6.png",
        "price": 10.99,
        "category": "hoodie"
    },
    {
        "id": 167,
        "name": "Wholesale customization of your logo oversized street style blank hoodie and sweatshirt for kids",
        "image": "https://i.postimg.cc/j2Bc37nZ/7.png",
        "price": 10.99,
        "category": "hoodie"
    },
    {
        "id": 168,
        "name": "Wholesale customization of your logo oversized street style blank hoodie and sweatshirt for kids",
        "image": "https://i.postimg.cc/66PMpDbn/8.png",
        "price": 10.99,
        "category": "hoodie"
    },
    {
        "id": 169,
        "name": "Wholesale customization of your logo oversized street style blank hoodie and sweatshirt for kids",
        "image": "https://i.postimg.cc/vH63g3Cj/9.png",
        "price": 10.99,
        "category": "hoodie"
    },
    {
        "id": 170,
        "name": "Wholesale customization of your logo oversized street style blank hoodie and sweatshirt for kids",
        "image": "https://i.postimg.cc/9Q51Gyhf/10.png",
        "price": 10.99,
        "category": "hoodie"
    },
    {
        "id": 171,
        "name": "Wholesale customization of your logo oversized street style blank hoodie and sweatshirt for kids",
        "image": "https://i.postimg.cc/4x6PwnfQ/11.png",
        "price": 10.99,
        "category": "hoodie"
    },
    {
        "id": 172,
        "name": "Wholesale customization of your logo oversized street style blank hoodie and sweatshirt for kids",
        "image": "https://i.postimg.cc/fbMKPZkn/12.png",
        "price": 10.99,
        "category": "hoodie"
    },
    {
        "id": 173,
        "name": "Wholesale customization of your logo oversized street style blank hoodie and sweatshirt for kids",
        "image": "https://i.postimg.cc/43w5kMhK/13.png",
        "price": 10.99,
        "category": "hoodie"
    },
    {
        "id": 174,
        "name": "Wholesale customization of your logo oversized street style blank hoodie and sweatshirt for kids",
        "image": "https://i.postimg.cc/XJJgV8ws/14.png",
        "price": 10.99,
        "category": "hoodie"
    },
    {
        "id": 175,
        "name": "Wholesale customization of your logo oversized street style blank hoodie and sweatshirt for kids",
        "image": "https://i.postimg.cc/G25x9yKd/15.png",
        "price": 10.99,
        "category": "hoodie"
    },
    {
        "id": 176,
        "name": "Wholesale customization of your logo oversized street style blank hoodie and sweatshirt for kids",
        "image": "https://i.postimg.cc/6q4LZpbR/16.png",
        "price": 10.99,
        "category": "hoodie"
    },
    {
        "id": 177,
        "name": "Wholesale customization of your logo oversized street style blank hoodie and sweatshirt for kids",
        "image": "https://i.postimg.cc/2j1PGdPd/17.png",
        "price": 10.99,
        "category": "hoodie"
    },
    {
        "id": 178,
        "name": "Wholesale customization of your logo oversized street style blank hoodie and sweatshirt for kids",
        "image": "https://i.postimg.cc/23pd7Ngt/18.png",
        "price": 10.99,
        "category": "hoodie"
    },
    {
        "id": 179,
        "name": "Wholesale customization of your logo oversized street style blank hoodie and sweatshirt for kids",
        "image": "https://i.postimg.cc/66FFm2Xk/19.png",
        "price": 10.99,
        "category": "hoodie"
    },
    {
        "id": 180,
        "name": "Wholesale customization of your logo oversized street style blank hoodie and sweatshirt for kids",
        "image": "https://i.postimg.cc/fTX1nzWJ/20.png",
        "price": 10.99,
        "category": "hoodie"
    },
    {
        "id": 181,
        "name": "High Quality winter wear for kids",
        "image": "https://i.postimg.cc/qRCJnfrS/1.png",
        "price": 10.99,
        "category": "winter"
    },
    {
        "id": 182,
        "name": "High Quality winter wear for  kids",
        "image": "https://i.postimg.cc/mZCZgG8F/2.png",
        "price": 10.99,
        "category": "winter"
    },
    {
        "id": 183,
        "name": "High Quality winter wear for  kids",
        "image": "https://i.postimg.cc/mgXB5Z2K/3.png",
        "price": 10.99,
        "category": "winter"
    },
    {
        "id": 184,
        "name": "High Quality winter wear for  kids",
        "image": "https://i.postimg.cc/4xNXPHZz/4.png",
        "price": 10.99,
        "category": "hoodie"
    },
    {
        "id": 185,
        "name": "High Quality winter wear for  kids",
        "image": "https://i.postimg.cc/hjxnv9bq/5.png",
        "price": 10.99,
        "category": "winter"
    },
    {
        "id": 186,
        "name": "High Quality winter wear for  kids",
        "image": "https://i.postimg.cc/PJQkzTR3/6.png",
        "price": 10.99,
        "category": "winter"
    },
    {
        "id": 187,
        "name": "High Quality winter wear for  kids",
        "image": "https://i.postimg.cc/RC79zLZ7/7.png",
        "price": 10.99,
        "category": "winter"
    },
    {
        "id": 188,
        "name": "High Quality winter wear for  kids",
        "image": "https://i.postimg.cc/zXpryDW3/8.png",
        "price": 10.99,
        "category": "winter"
    },
    {
        "id": 189,
        "name": "High Quality winter wear for  kids",
        "image": "https://i.postimg.cc/G200W40g/9.png",
        "price": 10.99,
        "category": "winter"
    },
    {
        "id": 190,
        "name": "High Quality winter wear for  kids",
        "image": "https://i.postimg.cc/0QpgP9Pk/10.png",
        "price": 10.99,
        "category": "winter"
    },
    {
        "id": 191,
        "name": "High Quality winter wear for  kids",
        "image": "https://i.postimg.cc/7hVpJX5j/11.png",
        "price": 10.99,
        "category": "winter"
    },
    {
        "id": 192,
        "name": "High Quality winter wear for  kids",
        "image": "https://i.postimg.cc/rwzvz1MY/12.png",
        "price": 10.99,
        "category": "winter"
    },
    {
        "id": 193,
        "name": "High Quality winter wear for  kids",
        "image": "https://i.postimg.cc/BnyRFjvZ/13.png",
        "price": 10.99,
        "category": "winter"
    },
    {
        "id": 194,
        "name": "High Quality winter wear for  kids",
        "image": "https://i.postimg.cc/xCGZBg3q/14.png",
        "price": 10.99,
        "category": "winter"
    },
    {
        "id": 195,
        "name": "High Quality winter wear for  kids",
        "image": "https://i.postimg.cc/1RHTHCzj/15.png",
        "price": 10.99,
        "category": "winter"
    },
    {
        "id": 196,
        "name": "High Quality winter wear for kids",
        "image": "https://i.postimg.cc/QN045F4L/16.png",
        "price": 10.99,
        "category": "winter"
    },
    {
        "id": 197,
        "name": "High Quality winter wear for  kids",
        "image": "https://i.postimg.cc/rsnfLH0y/17.png",
        "price": 10.99,
        "category": "winter"
    },
    {
        "id": 198,
        "name": "High Quality winter wear for  kids",
        "image": "https://i.postimg.cc/j5RcnTyd/18.png",
        "price": 10.99,
        "category": "winter"
    },
    {
        "id": 199,
        "name": "High Quality winter wear for  kids",
        "image": "https://i.postimg.cc/pdfkdrh6/19.png",
        "price": 10.99,
        "category": "winter"
    },
    {
        "id": 200,
        "name": "High Quality winter wear for kids",
        "image": "https://i.postimg.cc/V6TgNVBK/20.png",
        "price": 10.99,
        "category": "winter"
    },
    {
        "id": 201,
        "name": "Wholesale Suit Pants trouser  Formal Pants Summer Drape Embroidery Elastic Waist Casual  kid's truser",
        "image": "https://i.postimg.cc/G2Y9TzZL/1.png",
        "price": 10.99,
        "category": "trouser"
    },
    {
        "id": 202,
        "name": "Wholesale Suit Pants trouser  Formal Pants Summer Drape Embroidery Elastic Waist Casual  kid's truser",
        "image": "https://i.postimg.cc/Pq0Pq0VV/2.png",
        "price": 10.99,
        "category": "trouser"
    },
    {
        "id": 203,
        "name": "Wholesale Suit Pants trouser  Formal Pants Summer Drape Embroidery Elastic Waist Casual  kid's truser",
        "image": "https://i.postimg.cc/YCnv5v6H/3.png",
        "price": 10.99,
        "category": "trouser"
    },
    {
        "id": 204,
        "name": "Wholesale Suit Pants trouser Formal Pants Summer Drape Embroidery Elastic Waist Casual  kid's truser",
        "image": "https://i.postimg.cc/FKYYNhpJ/4.png",
        "price": 10.99,
        "category": "trouser"
    },
    {
        "id": 205,
        "name": "Wholesale Suit Pants trouser  Formal Pants Summer Drape Embroidery Elastic Waist Casual kid's truser",
        "image": "https://i.postimg.cc/L5p5tLpz/5.png",
        "price": 10.99,
        "category": "shirt"
    },
    {
        "id": 206,
        "name": "Wholesale Suit Pants trouser  Formal Pants Summer Drape Embroidery Elastic Waist Casual  kids truser",
        "image": "https://i.postimg.cc/2y762ykg/6.png",
        "price": 10.99,
        "category": "trouser"
    },
    {
        "id": 207,
        "name": "Wholesale Suit Pants trouser  Formal Pants Summer Drape Embroidery Elastic Waist Casual  kid's truser",
        "image": "https://i.postimg.cc/FFy79WyG/7.png",
        "price": 10.99,
        "category": "trouser"
    },
    {
        "id": 208,
        "name": "Wholesale Suit Pants trouser  Formal Pants Summer Drape Embroidery Elastic Waist Casual  kid's truser",
        "image": "https://i.postimg.cc/c4TC3v5n/8.png",
        "price": 10.99,
        "category": "trouser"
    },
    {
        "id": 209,
        "name": "Wholesale Suit Pants trouser  Formal Pants Summer Drape Embroidery Elastic Waist Casual  kid's truser",
        "image": "https://i.postimg.cc/6pmQHDK6/9.png",
        "price": 10.99,
        "category": "trouser"
    },
    {
        "id": 210,
        "name": "Wholesale Suit Pants trouser  Formal Pants Summer Drape Embroidery Elastic Waist Casual  kid's truser",
        "image": "https://i.postimg.cc/2S667CPX/10.png",
        "price": 10.99,
        "category": "trouser"
    },
    {
        "id": 211,
        "name": "Wholesale Suit Pants trouser  Formal Pants Summer Drape Embroidery Elastic Waist Casual  kid's truser",
        "image": "https://i.postimg.cc/Pqv502fW/11.png",
        "price": 10.99,
        "category": "trouser"
    },
    {
        "id": 212,
        "name": "Wholesale Suit Pants trouser  Formal Pants Summer Drape Embroidery Elastic Waist Casual  kid's truser",
        "image": "https://i.postimg.cc/8cNkJGR4/12.png",
        "price": 10.99,
        "category": "trouser"
    },
    {
        "id": 213,
        "name": "Wholesale Suit Pants trouser  Formal Pants Summer Drape Embroidery Elastic Waist Casual  kids truser",
        "image": "https://i.postimg.cc/mkjL7nVs/13.png",
        "price": 10.99,
        "category": "trouser"
    },
    {
        "id": 214,
        "name": "Wholesale Suit Pants trouser  Formal Pants Summer Drape Embroidery Elastic Waist Casual  kid's truser",
        "image": "https://i.postimg.cc/mDxg4Ch0/14.png",
        "price": 10.99,
        "category": "trouser"
    },
    {
        "id": 215,
        "name": "Wholesale Suit Pants trouser Formal Pants Summer Drape Embroidery Elastic Waist Casual  kid's truser",
        "image": "https://i.postimg.cc/76gYZh2b/15.png",
        "price": 10.99,
        "category": "trouser"
    },
    {
        "id": 216,
        "name": "Wholesale Suit Pants trouser  Formal Pants Summer Drape Embroidery Elastic Waist Casual  kid's truser",
        "image": "https://i.postimg.cc/ZYx5k9mM/16.png",
        "price": 10.99,
        "category": "trouser"
    },
    {
        "id": 217,
        "name": "Wholesale Suit Pants trouser Formal Pants Summer Drape Embroidery Elastic Waist Casual  kid's truser",
        "image": "https://i.postimg.cc/DyCfZt8Q/17.png",
        "price": 10.99,
        "category": "trouser"
    },
    {
        "id": 218,
        "name": "Wholesale Suit Pants trouser  Formal Pants Summer Drape Embroidery Elastic Waist Casual  kid's truser",
        "image": "https://i.postimg.cc/jdqdRsdd/18.png",
        "price": 10.99,
        "category": "trouser"
    },
    {
        "id": 219,
        "name": "Wholesale Suit Pants trouser Formal Pants Summer Drape Embroidery Elastic Waist Casual  kid's truser",
        "image": "https://i.postimg.cc/dVpqRrRL/19.png",
        "price": 10.99,
        "category": "trouser"
    },
    {
        "id": 220,
        "name": "Wholesale Suit Pants trouser  kid's Business Formal Pants Summer Drape Embroidery Elastic Waist Casual kid's truser",
        "image": "https://i.postimg.cc/g2nz6NZC/20.png",
        "price": 10.99,
        "category": "trouser"
    },
    {
        "id": 221,
        "name": "High quality swimwear shirt suit and pants for kids boys and girls",
        "image": "https://i.postimg.cc/kgGtTQ0C/1.png",
        "price": 10.99,
        "category": "swimwear"
    },
    {
        "id": 222,
        "name": "High quality swimwear shirt suit and pants for kids boys and girls",
        "image": "https://i.postimg.cc/SKzYhyQt/2.png",
        "price": 10.99,
        "category": "swimwear"
    },
    {
        "id": 223,
        "name": "High quality swimwear shirt suit and pants for kids boys and girls",
        "image": "https://i.postimg.cc/2StLMqYZ/3.png",
        "price": 10.99,
        "category": "swimwear"
    },
    {
        "id": 224,
        "name": "High quality swimwear shirt suit and pants for kids boys and girls",
        "image": "https://i.postimg.cc/PxspfBPf/4.png",
        "price": 10.99,
        "category": "swimwear"
    },
    {
        "id": 225,
        "name": "High quality swimwear shirt suit and pants for kids boys and girls",
        "image": "https://i.postimg.cc/pTf9mqFf/5.png",
        "price": 10.99,
        "category": "swimwear"
    },
    {
        "id": 226,
        "name": "High quality swimwear shirt suit and pants for kids boys and girls",
        "image": "https://i.postimg.cc/QCjF11QR/6.png",
        "price": 10.99,
        "category": "swimwear"
    },
    {
        "id": 227,
        "name": "High quality swimwear shirt suit and pants for kids boys and girls",
        "image": "https://i.postimg.cc/C5JzN5Jd/7.png",
        "price": 10.99,
        "category": "swimwear"
    },
    {
        "id": 228,
        "name": "High quality swimwear shirt suit and pants for kids boys and girls",
        "image": "https://i.postimg.cc/NGx9YCYY/8.png",
        "price": 10.99,
        "category": "swimwear"
    },
    {
        "id": 229,
        "name": "High quality swimwear shirt suit and pants for kids boys and girls",
        "image": "https://i.postimg.cc/m22cr329/9.png",
        "price": 10.99,
        "category": "swimwear"
    },
    {
        "id": 230,
        "name": "High quality swimwear shirt suit and pants for kids boys and girls",
        "image": "https://i.postimg.cc/TY7K5yp4/10.png",
        "price": 10.99,
        "category": "swimwear"
    },
    {
        "id": 231,
        "name": "High quality swimwear shirt suit and pants for kids boys and girls",
        "image": "https://i.postimg.cc/fRVJcwdT/11.png",
        "price": 10.99,
        "category": "swimwear"
    },
    {
        "id": 232,
        "name": "WHigh quality swimwear shirt suit and pants for kids boys and girls",
        "image": "https://i.postimg.cc/K8C4Qd77/12.png",
        "price": 10.99,
        "category": "swimwear"
    },
    {
        "id": 233,
        "name": "High quality swimwear shirt suit and pants for kids boys and girls",
        "image": "https://i.postimg.cc/R0fhYXGk/13.png",
        "price": 10.99,
        "category": "swimwear"
    },
    {
        "id": 234,
        "name": "High quality swimwear shirt suit and pants for kids boys and girls",
        "image": "https://i.postimg.cc/C1g5pkQz/14.png",
        "price": 10.99,
        "category": "swimwear"
    },
    {
        "id": 235,
        "name": "High quality swimwear shirt suit and pants for kids boys and girls",
        "image": "https://i.postimg.cc/MTmT6HCt/15.png",
        "price": 10.99,
        "category": "swimwear"
    },
    {
        "id": 236,
        "name": "High quality swimwear shirt suit and pants for kids boys and girls",
        "image": "https://i.postimg.cc/gjc0nddp/16.png",
        "price": 10.99,
        "category": "swimwear"
    },
    {
        "id": 237,
        "name": "High quality swimwear shirt suit and pants for kids boys and girls",
        "image": "https://i.postimg.cc/hvCtmwPd/17.png",
        "price": 10.99,
        "category": "swimwear"
    },
    {
        "id": 238,
        "name": "High quality swimwear shirt suit and pants for kids boys and girls",
        "image": "https://i.postimg.cc/Y289T4fC/18.png",
        "price": 10.99,
        "category": "swimwear"
    },
    {
        "id": 239,
        "name": "High quality swimwear shirt suit and pants for kids boys and girls",
        "image": "https://i.postimg.cc/3x0xytMk/19.png",
        "price": 10.99,
        "category": "swimwear"
    },
    {
        "id": 240,
        "name": "High quality swimwear shirt suit and pants for kids boys and girls",
        "image": "https://i.postimg.cc/dtx0tzfM/20.png",
        "price": 10.99,
        "category": "swimwear"
    }

]